[
    {
        "text": "O que é que os fundadores da tuna estavam a comer na reunião de criação da tuna?",
        "options": [
            "Pizzas",
            "Hamburgueres",
            "Bifanas",
            "Tostas Mistas"
        ],
        "answer": "Tostas Mistas"
    },
    {
        "text": "Qual foi a data de fundação da TMIST?",
        "options": [
            "28 de Outubro de 2007",
            "16 de Setembro de 2006",
            "19 de Setembro de 2007",
            "19 de Setembro de 2006"
        ],
        "answer": "19 de Setembro de 2006"
    },
    {
        "text": "Quem escreveu a adaptação da \"A Problemática Colocação de um Mastro\" ?",
        "options": [
            "Senhor Teles",
            "Cera",
            "Skyfall",
            "Marty"
        ],
        "answer": "Blue"
    }
]